odoo/addons/project_sequence/README.rst
odoo/addons/project_sequence/__init__.py
odoo/addons/project_sequence/__manifest__.py
odoo/addons/project_sequence/data/ir_sequence.xml
odoo/addons/project_sequence/i18n/de.po
odoo/addons/project_sequence/i18n/es.po
odoo/addons/project_sequence/i18n/it.po
odoo/addons/project_sequence/i18n/nl.po
odoo/addons/project_sequence/i18n/project_sequence.pot
odoo/addons/project_sequence/i18n/pt_BR.po
odoo/addons/project_sequence/models/__init__.py
odoo/addons/project_sequence/models/project_project.py
odoo/addons/project_sequence/readme/CONFIGURE.md
odoo/addons/project_sequence/readme/CONTRIBUTORS.md
odoo/addons/project_sequence/readme/CREDITS.md
odoo/addons/project_sequence/readme/DESCRIPTION.md
odoo/addons/project_sequence/readme/USAGE.md
odoo/addons/project_sequence/static/description/icon.png
odoo/addons/project_sequence/static/description/index.html
odoo/addons/project_sequence/tests/__init__.py
odoo/addons/project_sequence/tests/test_project_sequence.py
odoo/addons/project_sequence/views/project_project.xml
odoo/addons/project_sequence/wizards/__init__.py
odoo/addons/project_sequence/wizards/res_config_settings.py
odoo/addons/project_sequence/wizards/res_config_settings_view.xml
odoo_addon_project_sequence-18.0.1.0.0.3.dist-info/METADATA
odoo_addon_project_sequence-18.0.1.0.0.3.dist-info/WHEEL
odoo_addon_project_sequence-18.0.1.0.0.3.dist-info/top_level.txt
odoo_addon_project_sequence-18.0.1.0.0.3.dist-info/RECORD
